schrutepy/__init__.py
schrutepy/schrutepy.py
schrutepy-0.1.1.dist-info/METADATA
schrutepy-0.1.1.dist-info/WHEEL
schrutepy-0.1.1.dist-info/top_level.txt
schrutepy-0.1.1.dist-info/RECORD
