Metadata-Version: 2.1
Name: schrutepy
Version: 0.1.1
Summary: The Entire Transcripts from the Office in Tidy Format
Home-page: https://github.com/bradlindblad/schrutepy
Author: Brad Lindblad
Author-email: bradley.lindblad@gmail.com
License: UNKNOWN
Platform: UNKNOWN
Classifier: Programming Language :: Python :: 3.6
Classifier: License :: OSI Approved :: GNU General Public License v3 (GPLv3)
Requires-Dist: ipython (>=6)
Requires-Dist: twine (>=3)
Requires-Dist: wheel
Requires-Dist: pip
Requires-Dist: pandas
